cas2iob/__init__.py
cas2iob/cas2iob.py
cas2iob-0.1.0.dist-info/LICENSE
cas2iob-0.1.0.dist-info/METADATA
cas2iob-0.1.0.dist-info/WHEEL
cas2iob-0.1.0.dist-info/entry_points.txt
cas2iob-0.1.0.dist-info/top_level.txt
cas2iob-0.1.0.dist-info/RECORD
