Metadata-Version: 2.1
Name: cas2iob
Version: 0.1.0
Summary: Converter of UIMA CAS XMI files from INCEpTION with nested NER tags, NEL tags and components into IOB TSV files
Home-page: https://github.com/UB-Mannheim/cas2iob
Author: Renat Shigapov
License: MIT
Classifier: Programming Language :: Python :: 3
Classifier: License :: OSI Approved :: MIT License
Classifier: Operating System :: OS Independent
Requires-Python: >=3.7
License-File: LICENSE
Requires-Dist: typer[all]
Requires-Dist: tqdm
Requires-Dist: dkpro-cassis
